raindancesvi/__init__.py
raindancesvi/_gen_utils.py
raindancesvi/_inclass_utils.py
raindancesvi/_inclassnet.py
raindancesvi/_losses.py
raindancesvi-0.1.0.dist-info/LICENSE
raindancesvi-0.1.0.dist-info/METADATA
raindancesvi-0.1.0.dist-info/WHEEL
raindancesvi-0.1.0.dist-info/top_level.txt
raindancesvi-0.1.0.dist-info/RECORD
