Metadata-Version: 2.1
Name: raindancesvi
Version: 0.1.0
Summary: A machine learning package
Home-page: https://prasanthcakewalk.gitlab.io/raindancesvi
Author: Prasanth Shyamsundar
Author-email: prasanth.s.cmi@gmail.com
License: MIT
Keywords: machine learning rd6 inclass raindances
Platform: any
Classifier: Programming Language :: Python :: 3
Classifier: License :: OSI Approved :: MIT License
Classifier: Operating System :: OS Independent
Classifier: Development Status :: 3 - Alpha
Requires-Python: >=3.6
Requires-Dist: numpy
Requires-Dist: tensorflow (>=2)
